streamlit_star_rating/__init__.py
streamlit_star_rating/frontend/build/asset-manifest.json
streamlit_star_rating/frontend/build/bootstrap.min.css
streamlit_star_rating/frontend/build/index.html
streamlit_star_rating/frontend/build/precache-manifest.a982ecc6e1bfb804d4fb37038240d2af.js
streamlit_star_rating/frontend/build/precache-manifest.f25caae44a80dcc0ba1ebb5511dccb6c.js
streamlit_star_rating/frontend/build/service-worker.js
streamlit_star_rating/frontend/build/static/js/2.76da4152.chunk.js
streamlit_star_rating/frontend/build/static/js/2.76da4152.chunk.js.LICENSE.txt
streamlit_star_rating/frontend/build/static/js/2.76da4152.chunk.js.map
streamlit_star_rating/frontend/build/static/js/2.8a4f6c6d.chunk.js
streamlit_star_rating/frontend/build/static/js/2.8a4f6c6d.chunk.js.LICENSE.txt
streamlit_star_rating/frontend/build/static/js/2.8a4f6c6d.chunk.js.map
streamlit_star_rating/frontend/build/static/js/main.6fe35020.chunk.js
streamlit_star_rating/frontend/build/static/js/main.6fe35020.chunk.js.map
streamlit_star_rating/frontend/build/static/js/main.9ac02dd7.chunk.js
streamlit_star_rating/frontend/build/static/js/main.9ac02dd7.chunk.js.map
streamlit_star_rating/frontend/build/static/js/runtime-main.044ed49b.js
streamlit_star_rating/frontend/build/static/js/runtime-main.044ed49b.js.map
streamlit_star_rating/frontend/build/static/js/runtime-main.0e210323.js
streamlit_star_rating/frontend/build/static/js/runtime-main.0e210323.js.map
st_star_rating-0.0.5.dist-info/METADATA
st_star_rating-0.0.5.dist-info/WHEEL
st_star_rating-0.0.5.dist-info/top_level.txt
st_star_rating-0.0.5.dist-info/RECORD
