Metadata-Version: 2.1
Name: st-star-rating
Version: 0.0.5
Summary: Streamlit Component for Star Ratings
Home-page: 
Author: 
Author-email: 
Requires-Python: >=3.6
Requires-Dist: streamlit (>=0.63)
